{
  "format": "ee_entity_model_v1",
  "texture_size": [
    64,
    64
  ],
  "camera": {
    "yaw": 225,
    "pitch": 0
  },
  "render": {
    "scale": 21,
    "center": [
      384,
      545
    ]
  },
  "parts": [
    {
      "name": "body",
      "pivot": [
        0,
        8,
        0
      ],
      "boxes": [
        {
          "origin": [
            -4,
            4,
            -6
          ],
          "size": [
            8,
            8,
            12
          ],
          "uv": [
            0,
            16
          ]
        }
      ]
    },
    {
      "name": "head",
      "pivot": [
        0,
        14,
        -8
      ],
      "boxes": [
        {
          "origin": [
            -5,
            10,
            -14
          ],
          "size": [
            10,
            8,
            8
          ],
          "uv": [
            0,
            0
          ]
        }
      ]
    },
    {
      "name": "shell",
      "pivot": [
        0,
        10,
        5
      ],
      "boxes": [
        {
          "origin": [
            -7,
            3,
            1
          ],
          "size": [
            14,
            14,
            7
          ],
          "uv": [
            32,
            0
          ]
        }
      ],
      "rotation": [
        0,
        0,
        0
      ]
    },
    {
      "name": "tentacle_l",
      "pivot": [
        -3,
        5,
        -8
      ],
      "boxes": [
        {
          "origin": [
            -5,
            0,
            -12
          ],
          "size": [
            2,
            5,
            5
          ],
          "uv": [
            40,
            22
          ]
        }
      ],
      "rotation": [
        15,
        0,
        0
      ]
    },
    {
      "name": "tentacle_r",
      "pivot": [
        3,
        5,
        -8
      ],
      "boxes": [
        {
          "origin": [
            3,
            0,
            -12
          ],
          "size": [
            2,
            5,
            5
          ],
          "uv": [
            40,
            22
          ]
        }
      ],
      "rotation": [
        15,
        0,
        0
      ]
    }
  ]
}